{
  "sections": {
    "main": {
      "type": "main-article",
      "blocks": {
        "featured_image": {
          "type": "featured_image",
          "settings": {
            "image_height": "adapt"
          }
        },
        "title": {
          "type": "title",
          "settings": {
            "blog_show_date": true,
            "blog_show_author": false
          }
        },
        "share": {
          "type": "share",
          "settings": {
            "share_label": "Share"
          }
        },
        "content": {
          "type": "content"
        }
      },
      "block_order": [
        "featured_image",
        "title",
        "share",
        "content"
      ]
    },
    "article_outro": {
      "type": "nagi-article-outro",
      "settings": {
        "eyebrow": "From nagi",
        "heading": "素肌によりそう、次の一歩へ。",
        "body": "読んでくださってありがとうございます。気になるアイテムや、ほかの読みものものぞいてみてください。あなたの毎日のお手入れが、少しでも心地よくなりますように。",
        "cta_1_label": "アイテムを見る",
        "cta_1_url": "shopify://collections/all",
        "cta_2_label": "ほかの読みもの",
        "cta_2_url": "shopify://blogs/journal"
      }
    },
    "article_carousel": {
      "type": "nagi-product-carousel",
      "settings": {
        "eyebrow": "Pick Up",
        "heading": "この記事で紹介したアイテム",
        "collection": "all",
        "products_count": 10
      }
    }
  },
  "order": [
    "main",
    "article_outro",
    "article_carousel"
  ]
}
